var alminhas={"type": "FeatureCollection","name": "braga","crs": { "type": "name", "properties": { "name": "urn:ogc:def:crs:OGC:1.3:CRS84" } },"features": [{ "type": "Feature", "properties": { "name": "Sé, Campo das Carvalheiras", "DESCRIÇÃO DO ORATÓRIO": "«Cruzeiro de encruzilhada (...) Soco quadrangular, constituído por sete degraus, em cujo centro se eleva base monolítica, prismática, com quatro almofadas molduradas, decoradas com motivos vitomórficos, suportando grande coluna monolítica de secção circular com base de duplo toro, fuste com o terço inferior decorado com elementos quadrilóbulos, sendo a parte restante estriada e o capitel coríntio. Encima-o esfera esquartejada sobre acrotério, sobrepujada por cruz arquiepiscopal, de secção quadrangular, moldurada e com as hastes rematadas por pontas de diamante (...)», SIPA", "FICHA INVENTÁRIO": "0142-BAR-BG", "FREGUESIA": "Sé", "LAT": "41.548947", "LONG": "-8.429237", "OBS": "https://docs.google.com/document/d/e/2PACX-1vQG3KMZ7wSge_aIUzlGJ6HY8_TSuKsiYfsQ8a6FJpjSm_mUoKmzRUQu97B6SZuKIWnYBjqeBbV5XeGC/pub", "PAINEL": "", "TIPOLOGIA": "Cruz", "gx_media_links": "https://doc-0o-58-mymaps.googleusercontent.com/untrusted/hostedimage/ohe0dbgcv9jn7mbp3tk1ghb69o/b5ubjvobdrgonm0kg08qjqqfec/1692387765250/3evDZZ2F1ONbZ8Mo7WuI6QKm2vmYGVzF/07330417508546578562/5ACnmet76bL8l5TiFrYygoXq1iYQSIdwj5o2J95Gr_7e2t8FLQcjX4pXN-2yE9AZjfOooKpmD9Vs7CM-GqQVayOSAhnRD_UANCPT09le-CwC72Fy9aSjszJEZ1jEeYo-yYQ6Fo--t4IBPpa-BXc3LwkJf3wgOCDgsxpYZA7Bx_kkWVfbRfWyedxzDb0WhHJyKv0u_UIigvIgQnhW_amjM539fnfqIWYa-SdtTx0KmLKecNyYYEic?session=0&fife" }, "geometry": { "type": "Point", "coordinates": [ -8.429237, 41.548947, 0.0 ] } }]};
